LIMEaid/__init__.py
LIMEaid/version.py
LIMEaid/controller/LIMEaid.py
LIMEaid/controller/__init__.py
LIMEaid/controller/fit_sklearn_models.py
LIMEaid/data/Most-_Recent-_Cohorts-_Scorecard-_Elements.csv
LIMEaid/data/salaries-by-region.csv
LIMEaid/model/__init__.py
LIMEaid/model/get_college_datasets.py
LIMEaid/model/load_college_dataset.py
LIMEaid/unittests/__init__.py
LIMEaid/unittests/test_get_college_datasets.py
LIMEaid/unittests/test_lime_display.py
LIMEaid/unittests/test_lime_fit.py
LIMEaid/unittests/test_run_ml_models_for_college_ds.py
LIMEaid/unittests/test_versionpy.py
LIMEaid/view/LIMEdisplay.py
LIMEaid/view/__init__.py
examples/LIME_Education_ex.py
examples/LIME_Iris_ex.py
examples/__init__.py
LIMEaid-1.0.dist-info/LICENSE
LIMEaid-1.0.dist-info/METADATA
LIMEaid-1.0.dist-info/WHEEL
LIMEaid-1.0.dist-info/top_level.txt
LIMEaid-1.0.dist-info/RECORD
