Metadata-Version: 2.1
Name: LIMEaid
Version: 1.0
Summary: LIMEaid is a tabular version of LIME
Home-page: http://github.com/pking70/LIMEaid
Author: sumanbh@uw.edu;javiers@uw.edu;pking70@uw.edu
Author-email: sumanbh@uw.edu
Maintainer: sumanbh@uw.edu;javiers@uw.edu;pking70@uw.edu
Maintainer-email: sumanbh@uw.edu
License: MIT
Platform: OS Independent
Classifier: Development Status :: 3 - Alpha
Classifier: Environment :: Console
Classifier: Intended Audience :: Science/Research
Classifier: License :: OSI Approved :: MIT License
Classifier: Operating System :: OS Independent
Classifier: Programming Language :: Python
Classifier: Topic :: Scientific/Engineering
Requires: numpy
Requires-Dist: numpy
